Workbook

Sheet Current Reality
B2: YOUR FINANCIAL REALITY CHECK
B4: INCOME SOURCES
B5: Source | C5: Monthly Pay | D5: Hours/Week | E5: Weeks/Month | F5: Effective $/Hour
B6: Fintech Webflow Dev (40hrs/wk) | C6: 2500 | D6: 40 | E6: 4.33 | F6: =IF(C6>0,C6/(D6*E6),0) -> 14.43418
B7: Startup Product Designer (17hrs/wk) | C7: 1250 | D7: 17 | E7: 4.33 | F7: =IF(C7>0,C7/(D7*E7),0) -> 16.981388
B8: Side Projects (sporadic) | C8: 500 | D8: 8 | E8: 4.33 | F8: =IF(C8>0,C8/(D8*E8),0) -> 14.43418
B9: TOTAL | C9: =SUM(C6:C8) -> 4250 | D9: =SUM(D6:D8) -> 65 | E9: 4.33 | F9: =IF(C9>0,C9/(D9*E9),0) -> 15.100373
B11: MONTHLY EXPENSES (estimate — update with your real numbers)
B12: Rent / Housing | C12: 1500
B13: Utilities & Internet | C13: 200
B14: Food & Groceries | C14: 400
B15: Transportation | C15: 150
B16: Subscriptions & Tools | C16: 100
B17: Insurance | C17: 200
B18: Debt Payments | C18: 200
B19: Personal / Misc | C19: 250
B20: TOTAL EXPENSES | C20: =SUM(C12:C19) -> 3000
B22: THE TRUTH IN NUMBERS
B23: Monthly Surplus / Deficit | C23: =C9-C20 -> 1250
B24: Total Hours Worked Per Week | C24: =D9 -> 65
B25: Blended Effective Hourly Rate | C25: =F9 -> 15.100373
B26: Annual Income (at current pace) | C26: =C9*12 -> 51000
B28: ^ Blue numbers are YOUR inputs — update them with your real figures.

Sheet Scenario Comparison
B2: WHAT HAPPENS WHEN YOU MAKE A MOVE
C4: SCENARIO A Stay As-Is | D4: SCENARIO B Drop Design Role + 1 Project/Month | E4: SCENARIO C Drop Design Role + Raise Rate 30% + 1 Project/Month
B5: Fintech Role Income | C5: ='Current Reality'!C6 -> 2500 | D5: ='Current Reality'!C6 -> 2500 | E5: ='Current Reality'!C6*1.3 -> 3250
B6: Design Role Income | C6: ='Current Reality'!C7 -> 1250 | D6: 0 | E6: 0
B7: Side Projects Income | C7: ='Current Reality'!C8 -> 500 | D7: ='Current Reality'!C8 -> 500 | E7: ='Current Reality'!C8 -> 500
B8: Productized Project (1/mo) | C8: 0 | D8: 5000 | E8: 5000
B10: TOTAL MONTHLY INCOME | C10: =SUM(C5:C8) -> 4250 | D10: =SUM(D5:D8) -> 8000 | E10: =SUM(E5:E8) -> 8750
B11: Monthly Expenses | C11: ='Current Reality'!C20 -> 3000 | D11: ='Current Reality'!C20 -> 3000 | E11: ='Current Reality'!C20 -> 3000
B12: Monthly Surplus / Deficit | C12: =C10-C11 -> 1250 | D12: =D10-D11 -> 5000 | E12: =E10-E11 -> 5750
B14: Fintech Hours/Week | C14: ='Current Reality'!D6 -> 40 | D14: ='Current Reality'!D6 -> 40 | E14: ='Current Reality'!D6 -> 40
B15: Design Role Hours/Week | C15: ='Current Reality'!D7 -> 17 | D15: 0 | E15: 0
B16: Side Projects Hours/Week | C16: ='Current Reality'!D8 -> 8 | D16: ='Current Reality'!D8 -> 8 | E16: ='Current Reality'!D8 -> 8
B17: Productized Project Hrs/Week | C17: 0 | D17: 10 | E17: 10
B19: TOTAL HOURS/WEEK | C19: =SUM(C14:C17) -> 65 | D19: =SUM(D14:D17) -> 58 | E19: =SUM(E14:E17) -> 58
B20: Effective Hourly Rate | C20: =IF(C19>0,C10/(C19*4.33),0) -> 15.100373 | D20: =IF(D19>0,D10/(D19*4.33),0) -> 31.854742 | E20: =IF(E19>0,E10/(E19*4.33),0) -> 34.841124
B22: ANNUAL INCOME | C22: =C10*12 -> 51000 | D22: =D10*12 -> 96000 | E22: =E10*12 -> 105000
B23: Hours Freed Per Week | C23: 0 | D23: ='Current Reality'!D7 -> 17 | E23: ='Current Reality'!D7 -> 17
B26: WHAT THE NUMBERS SAY
B27: Scenario B: Drop the $1,250/mo design role, land ONE $5,000 Webflow project per month.
B28: Result: You earn significantly MORE, work FEWER hours, and free up ~17 hrs/week.
B29: Scenario C: Same as B, plus negotiate a 30% raise at fintech (still below market rate).
B30: That freed time is your runway to build a product or scale your offer.
B32: The design role costs you ~$17/hr. A single productized project at $5K for ~40hrs = $125/hr.
B33: You are currently trading $125/hr time for $17/hr work. That is the real cost.

Sheet 90-Day Action Plan
B2: YOUR 90-DAY ESCAPE PLAN
B4: WEEKS 1-2: FOUNDATION
B5: Status | C5: Action | D5: Details | E5: Target
B6: [ ] | C6: Calculate exact numbers | D6: Fill in Sheet 1 with real figures | E6: This week
B7: [ ] | C7: Define productized offer | D7: "Webflow marketing sites for SaaS/fintech — $5-7K, 2-3 weeks" | E7: Week 1
B8: [ ] | C8: Build simple portfolio page | D8: 3-5 best Webflow projects, results-focused | E8: Week 2
B9: [ ] | C9: Draft rate increase request | D9: For fintech role — aim for 30% increase | E9: Week 2
B11: WEEKS 3-4: POSITIONING
B12: Status | C12: Action | D12: Details | E12: Target
B13: [ ] | C13: Send rate increase request | D13: Professional, value-based conversation | E13: Week 3
B14: [ ] | C14: Create LinkedIn content plan | D14: 2 posts/week about Webflow + SaaS marketing | E14: Week 3
B15: [ ] | C15: Identify 30 target prospects | D15: Funded SaaS startups needing marketing sites | E15: Week 4
B16: [ ] | C16: Begin outbound outreach | D16: 10 personalized messages per week | E16: Week 4
B18: WEEKS 5-8: FIRST CLIENT
B19: Status | C19: Action | D19: Details | E19: Target
B20: [ ] | C20: Land first productized project | D20: Goal: 1 client at $5,000+ | E20: Week 5-8
B21: [ ] | C21: Give notice on design role | D21: Once first project is signed or in pipeline | E21: Week 6-8
B22: [ ] | C22: Deliver exceptional first project | D22: This becomes your case study + referral source | E22: Week 6-8
B23: [ ] | C23: Document your process | D23: Template everything for faster delivery next time | E23: Ongoing
B25: WEEKS 9-12: SCALE
B26: Status | C26: Action | D26: Details | E26: Target
B27: [ ] | C27: Land second project client | D27: Goal: consistent 1 project/month minimum | E27: Week 9-10
B28: [ ] | C28: Build referral system | D28: Ask first client for intro to 2 others | E28: Week 10
B29: [ ] | C29: Evaluate product opportunities | D29: What problems did you see across clients? | E29: Week 11
B30: [ ] | C30: Plan next quarter | D30: Double down on what's working | E30: Week 12
